content_gallery/__init__.py
content_gallery/admin.py
content_gallery/apps.py
content_gallery/fields.py
content_gallery/forms.py
content_gallery/image_data.py
content_gallery/models.py
content_gallery/settings.py
content_gallery/urls.py
content_gallery/utils.py
content_gallery/views.py
content_gallery/widgets.py
content_gallery/migrations/0001_initial.py
content_gallery/migrations/0002_auto_20170305_1520.py
content_gallery/migrations/0003_auto_20170305_1729.py
content_gallery/migrations/0004_auto_20170309_2234.py
content_gallery/migrations/0005_auto_20170320_0028.py
content_gallery/migrations/0006_auto_20170504_2334.py
content_gallery/migrations/0007_auto_20170616_1845.py
content_gallery/migrations/__init__.py
content_gallery/static/content_gallery/admin/css/content-gallery-admin.css
content_gallery/static/content_gallery/admin/css/content-gallery-admin.min.css
content_gallery/static/content_gallery/admin/css/content-gallery-inline-admin.css
content_gallery/static/content_gallery/admin/css/content-gallery-inline-admin.min.css
content_gallery/static/content_gallery/admin/img/add-image.png
content_gallery/static/content_gallery/admin/js/content-gallery-admin-view.js
content_gallery/static/content_gallery/admin/js/content-gallery-admin-view.min.js
content_gallery/static/content_gallery/admin/js/content-gallery-inline-admin.js
content_gallery/static/content_gallery/admin/js/content-gallery-inline-admin.min.js
content_gallery/static/content_gallery/css/content-gallery-view.css
content_gallery/static/content_gallery/css/content-gallery-view.min.css
content_gallery/static/content_gallery/css/content-gallery.css
content_gallery/static/content_gallery/css/content-gallery.min.css
content_gallery/static/content_gallery/img/0.gif
content_gallery/static/content_gallery/img/close-button.png
content_gallery/static/content_gallery/img/left-arrow-small.png
content_gallery/static/content_gallery/img/left-arrow.png
django_content_gallery-1.0.0b1.dist-info/DESCRIPTION.rst
django_content_gallery-1.0.0b1.dist-info/METADATA
django_content_gallery-1.0.0b1.dist-info/RECORD
django_content_gallery-1.0.0b1.dist-info/WHEEL
django_content_gallery-1.0.0b1.dist-info/metadata.json
django_content_gallery-1.0.0b1.dist-info/top_level.txt
