Metadata-Version: 2.0
Name: django-content-gallery
Version: 1.0.0b1
Summary: The Django application allows to attach a collection of images to objects of any model of any app
Home-page: https://github.com/Kemaweyan/django-content-gallery
Author: Taras Gaidukov
Author-email: kemaweyan@gmail.com
License: BSD-3-Clause
Keywords: django image gallery photo
Platform: UNKNOWN
Classifier: Framework :: Django :: 1.10
Classifier: Framework :: Django :: 1.11
Classifier: Development Status :: 4 - Beta
Classifier: Environment :: Web Environment
Classifier: Programming Language :: Python :: 3.4
Classifier: Programming Language :: Python :: 3.5
Classifier: Programming Language :: Python :: 3.6
Classifier: Intended Audience :: Developers
Classifier: Operating System :: OS Independent
Classifier: License :: OSI Approved :: BSD License
Classifier: Topic :: Software Development :: Libraries :: Python Modules
Requires-Dist: Django (>=1.10)
Requires-Dist: Pillow (>=3.0.0)
Requires-Dist: awesome-slugify (>=1.6)
Requires-Dist: django-admin-jqueryui112
Requires-Dist: python-magic (>=0.4.2)
